LICENSE.txt
MANIFEST.in
README.rst
setup.py
genstr/__init__.py
genstr/__version__.py
genstr/generate.py
randStringify.egg-info/PKG-INFO
randStringify.egg-info/SOURCES.txt
randStringify.egg-info/dependency_links.txt
randStringify.egg-info/top_level.txt