Metadata-Version: 1.1
Name: randStringify
Version: 1.2.0
Summary: Generate random Strings of defined length or words.
Home-page: https://github.com/famishedrover/randString
Author: Angryziber
Author-email: mudit.verma2014@gmail.com
License: MIT
Keywords: random String Genreation
Platform: UNKNOWN
Classifier: Development Status :: 3 - Alpha
Classifier: Intended Audience :: Developers
Classifier: Topic :: Software Development :: Build Tools
Classifier: License :: OSI Approved :: MIT License
Classifier: Programming Language :: Python :: 2
Classifier: Programming Language :: Python :: 2.7
